pybrahttp/__init__.py
pybrahttp/httpreq.py
pybrahttp-0.1.5.dist-info/LICENSE
pybrahttp-0.1.5.dist-info/METADATA
pybrahttp-0.1.5.dist-info/WHEEL
pybrahttp-0.1.5.dist-info/RECORD
