Metadata-Version: 2.1
Name: pybrahttp
Version: 0.1.5
Summary: Brainstorming package, manage http request.
License: MIT
Author: Brainstorming
Author-email: Support.erp@brainstorming.eu
Requires-Python: >=3.10,<4.0
Classifier: License :: OSI Approved :: MIT License
Classifier: Programming Language :: Python :: 3
Classifier: Programming Language :: Python :: 3.10
Classifier: Programming Language :: Python :: 3.11
Classifier: Programming Language :: Python :: 3.12
Requires-Dist: orjson (>=3.10.7,<4.0.0)
Requires-Dist: requests-oauthlib (>=2.0.0,<3.0.0)
